rjTools/__init__.py
rjTools/log_handler.py
rjTools/scheduler_task.py
rjTools/scheduler_ui.py
rjTools/utils.py
rjTools/utils_APScheduler.py
SchedulerUtils-1.2.2.dist-info/LICENSE
SchedulerUtils-1.2.2.dist-info/METADATA
SchedulerUtils-1.2.2.dist-info/WHEEL
SchedulerUtils-1.2.2.dist-info/top_level.txt
SchedulerUtils-1.2.2.dist-info/zip-safe
SchedulerUtils-1.2.2.dist-info/RECORD
