Metadata-Version: 2.1
Name: SchedulerUtils
Version: 1.2.2
Summary: SchedulerUtils
Home-page: https://github.com/StarsAaron
Author: Aaron
Author-email: 103514303@qq.com
License: MIT
Platform: UNKNOWN
Classifier: Programming Language :: Python :: 3
Classifier: License :: OSI Approved :: MIT License
Classifier: Operating System :: OS Independent
Requires-Dist: logbook
Requires-Dist: apscheduler
Requires-Dist: sqlalchemy
